djangosaml/__init__.py
djangosaml/urls.py
djangosaml/views.py
djangosaml/templates/djangosaml/denied.html
djangosaml/templates/djangosaml/signout.html
djangosaml-1.0.7.dist-info/AUTHORS.rst
djangosaml-1.0.7.dist-info/LICENSE
djangosaml-1.0.7.dist-info/METADATA
djangosaml-1.0.7.dist-info/WHEEL
djangosaml-1.0.7.dist-info/top_level.txt
djangosaml-1.0.7.dist-info/RECORD
